hexbytes/__init__.py
hexbytes/_utils.py
hexbytes/main.py
hexbytes/py.typed
hexbytes-1.2.1.dist-info/LICENSE
hexbytes-1.2.1.dist-info/METADATA
hexbytes-1.2.1.dist-info/WHEEL
hexbytes-1.2.1.dist-info/top_level.txt
hexbytes-1.2.1.dist-info/RECORD
