Metadata-Version: 2.1
Name: hexbytes
Version: 1.2.1
Summary: hexbytes: Python `bytes` subclass that decodes hex, with a readable console output
Home-page: https://github.com/ethereum/hexbytes
Author: The Ethereum Foundation
Author-email: snakecharmers@ethereum.org
License: MIT
Keywords: ethereum
Classifier: Development Status :: 5 - Production/Stable
Classifier: Intended Audience :: Developers
Classifier: License :: OSI Approved :: MIT License
Classifier: Natural Language :: English
Classifier: Programming Language :: Python :: 3
Classifier: Programming Language :: Python :: 3.8
Classifier: Programming Language :: Python :: 3.9
Classifier: Programming Language :: Python :: 3.10
Classifier: Programming Language :: Python :: 3.11
Classifier: Programming Language :: Python :: 3.12
Requires-Python: >=3.8, <4
License-File: LICENSE
Provides-Extra: dev
Requires-Dist: build>=0.9.0; extra == "dev"
Requires-Dist: bump_my_version>=0.19.0; extra == "dev"
Requires-Dist: ipython; extra == "dev"
Requires-Dist: mypy==1.10.0; extra == "dev"
Requires-Dist: pre-commit>=3.4.0; extra == "dev"
Requires-Dist: tox>=4.0.0; extra == "dev"
Requires-Dist: twine; extra == "dev"
Requires-Dist: wheel; extra == "dev"
Requires-Dist: sphinx>=5.3.0; extra == "dev"
Requires-Dist: sphinx_rtd_theme>=1.0.0; extra == "dev"
Requires-Dist: towncrier<22,>=21; extra == "dev"
Requires-Dist: eth_utils>=2.0.0; extra == "dev"
Requires-Dist: hypothesis<=6.31.6,>=3.44.24; extra == "dev"
Requires-Dist: pytest>=7.0.0; extra == "dev"
Requires-Dist: pytest-xdist>=2.4.0; extra == "dev"
Provides-Extra: docs
Requires-Dist: sphinx>=5.3.0; extra == "docs"
Requires-Dist: sphinx_rtd_theme>=1.0.0; extra == "docs"
Requires-Dist: towncrier<22,>=21; extra == "docs"
Provides-Extra: test
Requires-Dist: eth_utils>=2.0.0; extra == "test"
Requires-Dist: hypothesis<=6.31.6,>=3.44.24; extra == "test"
Requires-Dist: pytest>=7.0.0; extra == "test"
Requires-Dist: pytest-xdist>=2.4.0; extra == "test"
